LightningTime/Lightning.py
LightningTime/__init__.py
lightning_time-0.0.3.dist-info/LICENSE
lightning_time-0.0.3.dist-info/METADATA
lightning_time-0.0.3.dist-info/WHEEL
lightning_time-0.0.3.dist-info/top_level.txt
lightning_time-0.0.3.dist-info/RECORD
