Metadata-Version: 2.1
Name: lightning-time
Version: 0.0.3
Summary: A simple package to utilize Lightning Time in python
Author-email: Neil Hommes <qh4nveh@gmail.com>
Project-URL: Homepage, https://github.com/CygnusX-26/LightningTime
Project-URL: Issues, https://github.com/CygnusX-26/LightningTime/issues
Classifier: Programming Language :: Python :: 3
Classifier: License :: OSI Approved :: MIT License
Classifier: Operating System :: OS Independent
Requires-Python: >=3.8
License-File: LICENSE
